AUTHORS
CHANGES.rst
LICENSE
MANIFEST.in
README.rst
setup.cfg
setup.py
include/symcxx/basic.hpp
include/symcxx/core.hpp
include/symcxx/derived.hpp
include/symcxx/isprime.hpp
include/symcxx/matrix.hpp
include/symcxx/namespace.hpp
include/symcxx/types.inc
include/symcxx/types_atomic.inc
include/symcxx/types_nonatomic.inc
include/symcxx/types_nonatomic_args_stack.inc
include/symcxx/types_nonatomic_binary.inc
include/symcxx/types_nonatomic_binary_math_h.inc
include/symcxx/types_nonatomic_binary_relational.inc
include/symcxx/types_nonatomic_unary.inc
include/symcxx/types_nonatomic_unary_math_h.inc
src/basic.cpp
src/namespace.cpp
symcxx/__init__.py
symcxx/_release.py
symcxx/_symcxx.cpp
symcxx.egg-info/PKG-INFO
symcxx.egg-info/SOURCES.txt
symcxx.egg-info/dependency_links.txt
symcxx.egg-info/requires.txt
symcxx.egg-info/top_level.txt
symcxx/tests/__init__.py
symcxx/tests/test_lambdify.py
symcxx/tests/test_symcxx.py