Metadata-Version: 1.1
Name: symcxx
Version: 0.1.9
Summary:  symcxx is a minimal symbolic manipulation python package written in C++. 
Home-page: https://github.com/bjodah/symcxx
Author: Björn Dahlgren
Author-email: bjodah@DELETEMEgmail.com
License: BSD
Platform: UNKNOWN
Classifier: Development Status :: 3 - Alpha
Classifier: License :: OSI Approved :: BSD License
Classifier: Operating System :: OS Independent
Classifier: Topic :: Scientific/Engineering
Classifier: Topic :: Scientific/Engineering :: Mathematics
